setup.cfg
setup.py
yelp3/__init__.py
yelp3/client.py
yelp3/errors.py
yelp3.egg-info/PKG-INFO
yelp3.egg-info/SOURCES.txt
yelp3.egg-info/dependency_links.txt
yelp3.egg-info/requires.txt
yelp3.egg-info/top_level.txt