Metadata-Version: 1.0
Name: yelp3
Version: 1.0.1
Summary: Python implementation of the Yelp V3 Fusion API
Home-page: https://github.com/tapslash/yelp3-python
Author: David Hargat
Author-email: davidmhargat@gmail.com
License: MIT
Keywords: yelp
Platform: UNKNOWN
